Metadata-Version: 2.1
Name: Perceptron-PyPi-package-Jap-patel
Version: 0.0.2
Summary: its an implementation of perceptron
Home-page: https://github.com/Jap_patel/Perceptron_PyPi_package
Author: Jap_patel
Author-email: jappatel1704@gmail.com
License: UNKNOWN
Project-URL: Bug Tracker, https://github.com/Jap_patel/Perceptron_PyPi_package/issues
Platform: UNKNOWN
Classifier: Programming Language :: Python :: 3
Classifier: License :: OSI Approved :: MIT License
Classifier: Operating System :: OS Independent
Requires-Python: >=3.7
License-File: LICENSE
Requires-Dist: numpy
Requires-Dist: tqdm
